WordFP/WordFP.py
WordFP/__init__.py
WordFP/__main__.py
WordFP/fastsimilarity.py
WordFP/data/wordFP_full.pkl
WordFP-1.0.2.dist-info/LICENSE
WordFP-1.0.2.dist-info/METADATA
WordFP-1.0.2.dist-info/WHEEL
WordFP-1.0.2.dist-info/top_level.txt
WordFP-1.0.2.dist-info/RECORD
