Metadata-Version: 2.1
Name: WordFP
Version: 1.0.2
Summary: A new way to encode words and similarity calculate.
Home-page: https://github.com/jeffrichardchemistry/WordFP
Author: Jefferson Richard Dias
Author-email: jrichardquimica@gmail.com
License: GNU GPL
Keywords: Encode,natural language processing,artificial intelligence,fingerprint
Platform: UNKNOWN
Classifier: Intended Audience :: Developers
Classifier: Intended Audience :: Science/Research
Classifier: Topic :: Scientific/Engineering
Classifier: License :: OSI Approved :: GNU General Public License v3 (GPLv3)
Classifier: Natural Language :: English
Classifier: Operating System :: Microsoft :: Windows
Classifier: Operating System :: POSIX :: Linux
Classifier: Environment :: MacOS X
Classifier: Programming Language :: Python :: 3.8
Requires-Dist: numpy
Requires-Dist: numba
Requires-Dist: pandas
